saptiva_agents/__init__.py
saptiva_agents/_choices.py
saptiva_agents/_constants.py
saptiva_agents/_utils.py
saptiva_agents/agents/__init__.py
saptiva_agents/agents/_assistant_agent.py
saptiva_agents/agents/_base_chat_agent.py
saptiva_agents/agents/_code_executor_agent.py
saptiva_agents/agents/_task.py
saptiva_agents/base/__init__.py
saptiva_agents/base/_chat_agent.py
saptiva_agents/base/_classes.py
saptiva_agents/base/_handoff.py
saptiva_agents/base/_termination.py
saptiva_agents/code_executors/local/__init__.py
saptiva_agents/conditions/__init__.py
saptiva_agents/conditions/_terminations.py
saptiva_agents/core/__init__.py
saptiva_agents/core/_agent_id.py
saptiva_agents/core/_circuit_breaker.py
saptiva_agents/core/_closure_agent.py
saptiva_agents/core/_core.py
saptiva_agents/core/_default_topic.py
saptiva_agents/core/_message_context.py
saptiva_agents/core/_observability.py
saptiva_agents/core/_research_context.py
saptiva_agents/core/_research_models.py
saptiva_agents/core/_routed_agent.py
saptiva_agents/core/_single_threaded_agent_runtime.py
saptiva_agents/core/_singletons.py
saptiva_agents/core/_structured_logging.py
saptiva_agents/core/_topic.py
saptiva_agents/core/_type_subscription.py
saptiva_agents/core/model_context/__init__.py
saptiva_agents/core/model_context/_chat_completion_context.py
saptiva_agents/core/tools/__init__.py
saptiva_agents/core/tools/_static_workbench.py
saptiva_agents/core/tools/_workbench.py
saptiva_agents/file_surfer/__init__.py
saptiva_agents/file_surfer/_file_surfer.py
saptiva_agents/file_surfer/_markdown_file_browser.py
saptiva_agents/http/__init__.py
saptiva_agents/http/_http_tool.py
saptiva_agents/memory/__init__.py
saptiva_agents/memory/_base_memory.py
saptiva_agents/memory/_list_memory.py
saptiva_agents/memory/chromadb.py
saptiva_agents/memory/mem0/__init__.py
saptiva_agents/memory/mem0/_mem0.py
saptiva_agents/memory/redis/__init__.py
saptiva_agents/memory/redis/_redis_memory.py
saptiva_agents/messages/__init__.py
saptiva_agents-0.2.5.dist-info/licenses/LICENSE
saptiva_agents-0.2.5.dist-info/licenses/LICENSE-CODE
saptiva_agents-0.2.5.dist-info/licenses/NOTICE.md
saptiva_agents-0.2.5.dist-info/METADATA
saptiva_agents-0.2.5.dist-info/WHEEL
saptiva_agents-0.2.5.dist-info/top_level.txt
saptiva_agents-0.2.5.dist-info/RECORD
