Metadata-Version: 2.4
Name: saptiva-agents
Version: 0.2.5
Summary: Saptiva Agents Framework based on AutoGen v0.4+
License-Expression: MIT
Requires-Python: >=3.10
License-File: LICENSE-CODE
License-File: LICENSE
License-File: NOTICE.md
Requires-Dist: autogen-agentchat>=0.4.4
Requires-Dist: autogen-core>=0.4.4
Requires-Dist: autogen-ext[openai]>=0.4.4
Requires-Dist: fastapi
Requires-Dist: uvicorn
Requires-Dist: python-multipart
Requires-Dist: aiohttp
Requires-Dist: requests
Requires-Dist: python-dotenv
Provides-Extra: web-surfer
Requires-Dist: autogen-ext[web-surfer]>=0.4.4; extra == "web-surfer"
Provides-Extra: web-research
Requires-Dist: trafilatura>=1.9.0; extra == "web-research"
Provides-Extra: observability
Requires-Dist: opentelemetry-api>=1.25.0; extra == "observability"
Provides-Extra: dev
Requires-Dist: pytest>=7.4.0; extra == "dev"
Requires-Dist: pytest-asyncio>=0.21.0; extra == "dev"
Requires-Dist: pytest-cov>=4.1.0; extra == "dev"
Requires-Dist: pytest-mock>=3.12.0; extra == "dev"
Requires-Dist: pytest-timeout>=2.2.0; extra == "dev"
Requires-Dist: coverage[toml]>=7.3.0; extra == "dev"
Requires-Dist: ruff>=0.1.0; extra == "dev"
Provides-Extra: all
Requires-Dist: saptiva-agents[observability,web-research,web-surfer]; extra == "all"
Dynamic: license-file
